{
  "h": [
    {
      "id": "466862",
      "minute": "13",
      "result": "SavedShot",
      "X": "0.740999984741211",
      "Y": "0.34900001525878904",
      "xG": "0.016270799562335014",
      "player": "Matthew Cash",
      "h_a": "h",
      "player_id": "8864",
      "situation": "OpenPlay",
      "season": "2021",
      "shotType": "RightFoot",
      "match_id": "16694",
      "h_team": "Aston Villa",
      "a_team": "Tottenham",
      "h_goals": "0",
      "a_goals": "4",
      "date": "2022-04-09 16:30:00",
      "player_assisted": "Philippe Coutinho",
      "lastAction": "Pass"
    },
    {
      "id": "466865",
      "minute": "16",
      "result": "SavedShot",
      "X": "0.9209999847412109",
      "Y": "0.6830000305175781",
      "xG": "0.30837199091911316",
      "player": "Jacob Ramsey",
      "h_a": "h",
      "player_id": "8941",
      "situation": "OpenPlay",
      "season": "2021",
      "shotType": "LeftFoot",
      "match_id": "16694",
      "h_team": "Aston Villa",
      "a_team": "Tottenham",
      "h_goals": "0",
      "a_goals": "4",
      "date": "2022-04-09 16:30:00",
      "player_assisted": "Douglas Luiz",
      "lastAction": "TakeOn"
    },
    {
      "id": "466866",
      "minute": "18",
      "result": "SavedShot",
      "X": "0.764000015258789",
      "Y": "0.3160000038146973",
      "xG": "0.01727229915559292",
      "player": "John McGinn",
      "h_a": "h",
      "player_id": "7723",
      "situation": "FromCorner",
      "season": "2021",
      "shotType": "LeftFoot",
      "match_id": "16694",
      "h_team": "Aston Villa",
      "a_team": "Tottenham",
      "h_goals": "0",
      "a_goals": "4",
      "date": "2022-04-09 16:30:00",
      "player_assisted": "Lucas Digne",
      "lastAction": "Pass"
    },
    {
      "id": "466867",
      "minute": "27",
      "result": "SavedShot",
      "X": "0.9269999694824219",
      "Y": "0.4209999847412109",
      "xG": "0.33952200412750244",
      "player": "Danny Ings",
      "h_a": "h",
      "player_id": "986",
      "situation": "SetPiece",
      "season": "2021",
      "shotType": "RightFoot",
      "match_id": "16694",
      "h_team": "Aston Villa",
      "a_team": "Tottenham",
      "h_goals": "0",
      "a_goals": "4",
      "date": "2022-04-09 16:30:00",
      "player_assisted": "Philippe Coutinho",
      "lastAction": "Chipped"
    },
    {
      "id": "466868",
      "minute": "31",
      "result": "MissedShots",
      "X": "0.94",
      "Y": "0.46700000762939453",
      "xG": "0.12280499935150146",
      "player": "Ollie Watkins",
      "h_a": "h",
      "player_id": "8865",
      "situation": "OpenPlay",
      "season": "2021",
      "shotType": "Head",
      "match_id": "16694",
      "h_team": "Aston Villa",
      "a_team": "Tottenham",
      "h_goals": "0",
      "a_goals": "4",
      "date": "2022-04-09 16:30:00",
      "player_assisted": "Philippe Coutinho",
      "lastAction": "Cross"
    },
    {
      "id": "466869",
      "minute": "34",
      "result": "BlockedShot",
      "X": "0.855",
      "Y": "0.40799999237060547",
      "xG": "0.05337480083107948",
      "player": "Danny Ings",
      "h_a": "h",
      "player_id": "986",
      "situation": "FromCorner",
      "season": "2021",
      "shotType": "RightFoot",
      "match_id": "16694",
      "h_team": "Aston Villa",
      "a_team": "Tottenham",
      "h_goals": "0",
      "a_goals": "4",
      "date": "2022-04-09 16:30:00",
      "player_assisted": null,
      "lastAction": "None"
    },
    {
      "id": "466870",
      "minute": "35",
      "result": "SavedShot",
      "X": "0.909000015258789",
      "Y": "0.68",
      "xG": "0.05985280126333237",
      "player": "Ollie Watkins",
      "h_a": "h",
      "player_id": "8865",
      "situation": "OpenPlay",
      "season": "2021",
      "shotType": "LeftFoot",
      "match_id": "16694",
      "h_team": "Aston Villa",
      "a_team": "Tottenham",
      "h_goals": "0",
      "a_goals": "4",
      "date": "2022-04-09 16:30:00",
      "player_assisted": "Danny Ings",
      "lastAction": "Pass"
    },
    {
      "id": "466871",
      "minute": "36",
      "result": "MissedShots",
      "X": "0.955999984741211",
      "Y": "0.605999984741211",
      "xG": "0.09004180133342743",
      "player": "Danny Ings",
      "h_a": "h",
      "player_id": "986",
      "situation": "FromCorner",
      "season": "2021",
      "shotType": "RightFoot",
      "match_id": "16694",
      "h_team": "Aston Villa",
      "a_team": "Tottenham",
      "h_goals": "0",
      "a_goals": "4",
      "date": "2022-04-09 16:30:00",
      "player_assisted": "Ollie Watkins",
      "lastAction": "HeadPass"
    },
    {
      "id": "466872",
      "minute": "39",
      "result": "BlockedShot",
      "X": "0.8419999694824218",
      "Y": "0.615",
      "xG": "0.05475449934601784",
      "player": "Danny Ings",
      "h_a": "h",
      "player_id": "986",
      "situation": "OpenPlay",
      "season": "2021",
      "shotType": "RightFoot",
      "match_id": "16694",
      "h_team": "Aston Villa",
      "a_team": "Tottenham",
      "h_goals": "0",
      "a_goals": "4",
      "date": "2022-04-09 16:30:00",
      "player_assisted": "Douglas Luiz",
      "lastAction": "Pass"
    },
    {
      "id": "466873",
      "minute": "40",
      "result": "MissedShots",
      "X": "0.6980000305175781",
      "Y": "0.41700000762939454",
      "xG": "0.013701699674129486",
      "player": "Philippe Coutinho",
      "h_a": "h",
      "player_id": "488",
      "situation": "OpenPlay",
      "season": "2021",
      "shotType": "RightFoot",
      "match_id": "16694",
      "h_team": "Aston Villa",
      "a_team": "Tottenham",
      "h_goals": "0",
      "a_goals": "4",
      "date": "2022-04-09 16:30:00",
      "player_assisted": "John McGinn",
      "lastAction": "Pass"
    },
    {
      "id": "466876",
      "minute": "47",
      "result": "SavedShot",
      "X": "0.905",
      "Y": "0.2929999923706055",
      "xG": "0.042587101459503174",
      "player": "Matthew Cash",
      "h_a": "h",
      "player_id": "8864",
      "situation": "OpenPlay",
      "season": "2021",
      "shotType": "RightFoot",
      "match_id": "16694",
      "h_team": "Aston Villa",
      "a_team": "Tottenham",
      "h_goals": "0",
      "a_goals": "4",
      "date": "2022-04-09 16:30:00",
      "player_assisted": null,
      "lastAction": "None"
    },
    {
      "id": "466877",
      "minute": "48",
      "result": "BlockedShot",
      "X": "0.7959999847412109",
      "Y": "0.575",
      "xG": "0.025902800261974335",
      "player": "Philippe Coutinho",
      "h_a": "h",
      "player_id": "488",
      "situation": "OpenPlay",
      "season": "2021",
      "shotType": "RightFoot",
      "match_id": "16694",
      "h_team": "Aston Villa",
      "a_team": "Tottenham",
      "h_goals": "0",
      "a_goals": "4",
      "date": "2022-04-09 16:30:00",
      "player_assisted": "Danny Ings",
      "lastAction": "HeadPass"
    },
    {
      "id": "466878",
      "minute": "49",
      "result": "SavedShot",
      "X": "0.9319999694824219",
      "Y": "0.884000015258789",
      "xG": "0.044098298996686935",
      "player": "Philippe Coutinho",
      "h_a": "h",
      "player_id": "488",
      "situation": "DirectFreekick",
      "season": "2021",
      "shotType": "RightFoot",
      "match_id": "16694",
      "h_team": "Aston Villa",
      "a_team": "Tottenham",
      "h_goals": "0",
      "a_goals": "4",
      "date": "2022-04-09 16:30:00",
      "player_assisted": null,
      "lastAction": "Standard"
    },
    {
      "id": "466879",
      "minute": "49",
      "result": "BlockedShot",
      "X": "0.9690000152587891",
      "Y": "0.555",
      "xG": "0.12290500104427338",
      "player": "Danny Ings",
      "h_a": "h",
      "player_id": "986",
      "situation": "SetPiece",
      "season": "2021",
      "shotType": "Head",
      "match_id": "16694",
      "h_team": "Aston Villa",
      "a_team": "Tottenham",
      "h_goals": "0",
      "a_goals": "4",
      "date": "2022-04-09 16:30:00",
      "player_assisted": null,
      "lastAction": "Aerial"
    },
    {
      "id": "466882",
      "minute": "57",
      "result": "BlockedShot",
      "X": "0.914000015258789",
      "Y": "0.4329999923706055",
      "xG": "0.04194119945168495",
      "player": "Ezri Konsa Ngoyo",
      "h_a": "h",
      "player_id": "7726",
      "situation": "FromCorner",
      "season": "2021",
      "shotType": "OtherBodyPart",
      "match_id": "16694",
      "h_team": "Aston Villa",
      "a_team": "Tottenham",
      "h_goals": "0",
      "a_goals": "4",
      "date": "2022-04-09 16:30:00",
      "player_assisted": "Lucas Digne",
      "lastAction": "Cross"
    },
    {
      "id": "466883",
      "minute": "58",
      "result": "BlockedShot",
      "X": "0.884000015258789",
      "Y": "0.38",
      "xG": "0.013319499790668488",
      "player": "Ezri Konsa Ngoyo",
      "h_a": "h",
      "player_id": "7726",
      "situation": "FromCorner",
      "season": "2021",
      "shotType": "Head",
      "match_id": "16694",
      "h_team": "Aston Villa",
      "a_team": "Tottenham",
      "h_goals": "0",
      "a_goals": "4",
      "date": "2022-04-09 16:30:00",
      "player_assisted": "Lucas Digne",
      "lastAction": "Cross"
    },
    {
      "id": "466884",
      "minute": "58",
      "result": "MissedShots",
      "X": "0.78",
      "Y": "0.6559999847412109",
      "xG": "0.028811300173401833",
      "player": "Danny Ings",
      "h_a": "h",
      "player_id": "986",
      "situation": "FromCorner",
      "season": "2021",
      "shotType": "RightFoot",
      "match_id": "16694",
      "h_team": "Aston Villa",
      "a_team": "Tottenham",
      "h_goals": "0",
      "a_goals": "4",
      "date": "2022-04-09 16:30:00",
      "player_assisted": "Lucas Digne",
      "lastAction": "Pass"
    },
    {
      "id": "466888",
      "minute": "88",
      "result": "MissedShots",
      "X": "0.855",
      "Y": "0.549000015258789",
      "xG": "0.05511989817023277",
      "player": "Leon Bailey",
      "h_a": "h",
      "player_id": "5221",
      "situation": "OpenPlay",
      "season": "2021",
      "shotType": "LeftFoot",
      "match_id": "16694",
      "h_team": "Aston Villa",
      "a_team": "Tottenham",
      "h_goals": "0",
      "a_goals": "4",
      "date": "2022-04-09 16:30:00",
      "player_assisted": null,
      "lastAction": "None"
    },
    {
      "id": "466889",
      "minute": "91",
      "result": "SavedShot",
      "X": "0.955",
      "Y": "0.32",
      "xG": "0.03647109866142273",
      "player": "Emiliano Buendía",
      "h_a": "h",
      "player_id": "2203",
      "situation": "FromCorner",
      "season": "2021",
      "shotType": "LeftFoot",
      "match_id": "16694",
      "h_team": "Aston Villa",
      "a_team": "Tottenham",
      "h_goals": "0",
      "a_goals": "4",
      "date": "2022-04-09 16:30:00",
      "player_assisted": "Douglas Luiz",
      "lastAction": "Cross"
    }
  ],
  "a": [
    {
      "id": "466860",
      "minute": "2",
      "result": "MissedShots",
      "X": "0.8109999847412109",
      "Y": "0.5279999923706055",
      "xG": "0.050093598663806915",
      "player": "Harry Kane",
      "h_a": "a",
      "player_id": "647",
      "situation": "OpenPlay",
      "season": "2021",
      "shotType": "RightFoot",
      "match_id": "16694",
      "h_team": "Aston Villa",
      "a_team": "Tottenham",
      "h_goals": "0",
      "a_goals": "4",
      "date": "2022-04-09 16:30:00",
      "player_assisted": null,
      "lastAction": "None"
    },
    {
      "id": "466861",
      "minute": "2",
      "result": "Goal",
      "X": "0.85",
      "Y": "0.5029999923706054",
      "xG": "0.06764789670705795",
      "player": "Son Heung-Min",
      "h_a": "a",
      "player_id": "453",
      "situation": "OpenPlay",
      "season": "2021",
      "shotType": "LeftFoot",
      "match_id": "16694",
      "h_team": "Aston Villa",
      "a_team": "Tottenham",
      "h_goals": "0",
      "a_goals": "4",
      "date": "2022-04-09 16:30:00",
      "player_assisted": null,
      "lastAction": "Rebound"
    },
    {
      "id": "466863",
      "minute": "14",
      "result": "BlockedShot",
      "X": "0.8640000152587891",
      "Y": "0.6530000305175782",
      "xG": "0.07377990335226059",
      "player": "Matt Doherty",
      "h_a": "a",
      "player_id": "6852",
      "situation": "OpenPlay",
      "season": "2021",
      "shotType": "RightFoot",
      "match_id": "16694",
      "h_team": "Aston Villa",
      "a_team": "Tottenham",
      "h_goals": "0",
      "a_goals": "4",
      "date": "2022-04-09 16:30:00",
      "player_assisted": "Harry Kane",
      "lastAction": "Pass"
    },
    {
      "id": "466864",
      "minute": "14",
      "result": "BlockedShot",
      "X": "0.750999984741211",
      "Y": "0.6129999923706054",
      "xG": "0.01916849985718727",
      "player": "Pierre-Emile Højbjerg",
      "h_a": "a",
      "player_id": "343",
      "situation": "OpenPlay",
      "season": "2021",
      "shotType": "RightFoot",
      "match_id": "16694",
      "h_team": "Aston Villa",
      "a_team": "Tottenham",
      "h_goals": "0",
      "a_goals": "4",
      "date": "2022-04-09 16:30:00",
      "player_assisted": null,
      "lastAction": "Rebound"
    },
    {
      "id": "466874",
      "minute": "42",
      "result": "SavedShot",
      "X": "0.8480000305175781",
      "Y": "0.6880000305175781",
      "xG": "0.0510408990085125",
      "player": "Sergio Reguilón",
      "h_a": "a",
      "player_id": "7187",
      "situation": "OpenPlay",
      "season": "2021",
      "shotType": "RightFoot",
      "match_id": "16694",
      "h_team": "Aston Villa",
      "a_team": "Tottenham",
      "h_goals": "0",
      "a_goals": "4",
      "date": "2022-04-09 16:30:00",
      "player_assisted": "Harry Kane",
      "lastAction": "Pass"
    },
    {
      "id": "466875",
      "minute": "43",
      "result": "BlockedShot",
      "X": "0.7719999694824219",
      "Y": "0.555",
      "xG": "0.020351899787783623",
      "player": "Pierre-Emile Højbjerg",
      "h_a": "a",
      "player_id": "343",
      "situation": "FromCorner",
      "season": "2021",
      "shotType": "RightFoot",
      "match_id": "16694",
      "h_team": "Aston Villa",
      "a_team": "Tottenham",
      "h_goals": "0",
      "a_goals": "4",
      "date": "2022-04-09 16:30:00",
      "player_assisted": null,
      "lastAction": "None"
    },
    {
      "id": "466880",
      "minute": "49",
      "result": "BlockedShot",
      "X": "0.7909999847412109",
      "Y": "0.40400001525878904",
      "xG": "0.01589380018413067",
      "player": "Pierre-Emile Højbjerg",
      "h_a": "a",
      "player_id": "343",
      "situation": "FromCorner",
      "season": "2021",
      "shotType": "RightFoot",
      "match_id": "16694",
      "h_team": "Aston Villa",
      "a_team": "Tottenham",
      "h_goals": "0",
      "a_goals": "4",
      "date": "2022-04-09 16:30:00",
      "player_assisted": null,
      "lastAction": "Aerial"
    },
    {
      "id": "466881",
      "minute": "49",
      "result": "Goal",
      "X": "0.9069999694824219",
      "Y": "0.6819999694824219",
      "xG": "0.07911650091409683",
      "player": "Dejan Kulusevski",
      "h_a": "a",
      "player_id": "6691",
      "situation": "OpenPlay",
      "season": "2021",
      "shotType": "LeftFoot",
      "match_id": "16694",
      "h_team": "Aston Villa",
      "a_team": "Tottenham",
      "h_goals": "0",
      "a_goals": "4",
      "date": "2022-04-09 16:30:00",
      "player_assisted": "Harry Kane",
      "lastAction": "HeadPass"
    },
    {
      "id": "466885",
      "minute": "59",
      "result": "BlockedShot",
      "X": "0.93",
      "Y": "0.34",
      "xG": "0.10930799692869186",
      "player": "Harry Kane",
      "h_a": "a",
      "player_id": "647",
      "situation": "OpenPlay",
      "season": "2021",
      "shotType": "RightFoot",
      "match_id": "16694",
      "h_team": "Aston Villa",
      "a_team": "Tottenham",
      "h_goals": "0",
      "a_goals": "4",
      "date": "2022-04-09 16:30:00",
      "player_assisted": "Emerson",
      "lastAction": "Pass"
    },
    {
      "id": "466886",
      "minute": "65",
      "result": "Goal",
      "X": "0.855999984741211",
      "Y": "0.549000015258789",
      "xG": "0.3804149925708771",
      "player": "Son Heung-Min",
      "h_a": "a",
      "player_id": "453",
      "situation": "OpenPlay",
      "season": "2021",
      "shotType": "LeftFoot",
      "match_id": "16694",
      "h_team": "Aston Villa",
      "a_team": "Tottenham",
      "h_goals": "0",
      "a_goals": "4",
      "date": "2022-04-09 16:30:00",
      "player_assisted": "Harry Kane",
      "lastAction": "HeadPass"
    },
    {
      "id": "466887",
      "minute": "70",
      "result": "Goal",
      "X": "0.8619999694824219",
      "Y": "0.4620000076293945",
      "xG": "0.12158799916505814",
      "player": "Son Heung-Min",
      "h_a": "a",
      "player_id": "453",
      "situation": "OpenPlay",
      "season": "2021",
      "shotType": "RightFoot",
      "match_id": "16694",
      "h_team": "Aston Villa",
      "a_team": "Tottenham",
      "h_goals": "0",
      "a_goals": "4",
      "date": "2022-04-09 16:30:00",
      "player_assisted": "Dejan Kulusevski",
      "lastAction": "Pass"
    }
  ]
}