{
  "h": [
    {
      "id": "263581",
      "minute": "14",
      "result": "SavedShot",
      "X": "0.725",
      "Y": "0.48700000762939455",
      "xG": "0.01596429944038391",
      "player": "James Maddison",
      "h_a": "h",
      "player_id": "6818",
      "situation": "OpenPlay",
      "season": "2018",
      "shotType": "RightFoot",
      "match_id": "9392",
      "h_team": "Leicester",
      "a_team": "Cardiff",
      "h_goals": "0",
      "a_goals": "1",
      "date": "2018-12-29 15:00:00",
      "player_assisted": "Harry Maguire",
      "lastAction": "TakeOn"
    },
    {
      "id": "263582",
      "minute": "17",
      "result": "MissedShots",
      "X": "0.9519999694824218",
      "Y": "0.44099998474121094",
      "xG": "0.0616689994931221",
      "player": "Wilfred Ndidi",
      "h_a": "h",
      "player_id": "5545",
      "situation": "FromCorner",
      "season": "2018",
      "shotType": "Head",
      "match_id": "9392",
      "h_team": "Leicester",
      "a_team": "Cardiff",
      "h_goals": "0",
      "a_goals": "1",
      "date": "2018-12-29 15:00:00",
      "player_assisted": "James Maddison",
      "lastAction": "Aerial"
    },
    {
      "id": "263583",
      "minute": "19",
      "result": "BlockedShot",
      "X": "0.7619999694824219",
      "Y": "0.33",
      "xG": "0.017470600083470345",
      "player": "Ricardo Pereira",
      "h_a": "h",
      "player_id": "3303",
      "situation": "OpenPlay",
      "season": "2018",
      "shotType": "LeftFoot",
      "match_id": "9392",
      "h_team": "Leicester",
      "a_team": "Cardiff",
      "h_goals": "0",
      "a_goals": "1",
      "date": "2018-12-29 15:00:00",
      "player_assisted": "James Maddison",
      "lastAction": "LayOff"
    },
    {
      "id": "263584",
      "minute": "22",
      "result": "MissedShots",
      "X": "0.7219999694824218",
      "Y": "0.49700000762939456",
      "xG": "0.01893630065023899",
      "player": "Demarai Gray",
      "h_a": "h",
      "player_id": "762",
      "situation": "OpenPlay",
      "season": "2018",
      "shotType": "RightFoot",
      "match_id": "9392",
      "h_team": "Leicester",
      "a_team": "Cardiff",
      "h_goals": "0",
      "a_goals": "1",
      "date": "2018-12-29 15:00:00",
      "player_assisted": "Nampalys Mendy",
      "lastAction": "Pass"
    },
    {
      "id": "263586",
      "minute": "24",
      "result": "BlockedShot",
      "X": "0.75",
      "Y": "0.3770000076293945",
      "xG": "0.015210200101137161",
      "player": "Wilfred Ndidi",
      "h_a": "h",
      "player_id": "5545",
      "situation": "OpenPlay",
      "season": "2018",
      "shotType": "RightFoot",
      "match_id": "9392",
      "h_team": "Leicester",
      "a_team": "Cardiff",
      "h_goals": "0",
      "a_goals": "1",
      "date": "2018-12-29 15:00:00",
      "player_assisted": null,
      "lastAction": "None"
    },
    {
      "id": "263587",
      "minute": "26",
      "result": "SavedShot",
      "X": "0.8090000152587891",
      "Y": "0.27",
      "xG": "0.02202400006353855",
      "player": "Ricardo Pereira",
      "h_a": "h",
      "player_id": "3303",
      "situation": "OpenPlay",
      "season": "2018",
      "shotType": "LeftFoot",
      "match_id": "9392",
      "h_team": "Leicester",
      "a_team": "Cardiff",
      "h_goals": "0",
      "a_goals": "1",
      "date": "2018-12-29 15:00:00",
      "player_assisted": "Marc Albrighton",
      "lastAction": "Pass"
    },
    {
      "id": "263588",
      "minute": "28",
      "result": "SavedShot",
      "X": "0.7530000305175781",
      "Y": "0.7119999694824218",
      "xG": "0.04261140152812004",
      "player": "James Maddison",
      "h_a": "h",
      "player_id": "6818",
      "situation": "DirectFreekick",
      "season": "2018",
      "shotType": "RightFoot",
      "match_id": "9392",
      "h_team": "Leicester",
      "a_team": "Cardiff",
      "h_goals": "0",
      "a_goals": "1",
      "date": "2018-12-29 15:00:00",
      "player_assisted": null,
      "lastAction": "Standard"
    },
    {
      "id": "263589",
      "minute": "40",
      "result": "SavedShot",
      "X": "0.8919999694824219",
      "Y": "0.720999984741211",
      "xG": "0.29936298727989197",
      "player": "Jamie Vardy",
      "h_a": "h",
      "player_id": "755",
      "situation": "OpenPlay",
      "season": "2018",
      "shotType": "LeftFoot",
      "match_id": "9392",
      "h_team": "Leicester",
      "a_team": "Cardiff",
      "h_goals": "0",
      "a_goals": "1",
      "date": "2018-12-29 15:00:00",
      "player_assisted": "James Maddison",
      "lastAction": "Throughball"
    },
    {
      "id": "263590",
      "minute": "42",
      "result": "MissedShots",
      "X": "0.9159999847412109",
      "Y": "0.5370000076293945",
      "xG": "0.03895070031285286",
      "player": "Jamie Vardy",
      "h_a": "h",
      "player_id": "755",
      "situation": "FromCorner",
      "season": "2018",
      "shotType": "Head",
      "match_id": "9392",
      "h_team": "Leicester",
      "a_team": "Cardiff",
      "h_goals": "0",
      "a_goals": "1",
      "date": "2018-12-29 15:00:00",
      "player_assisted": null,
      "lastAction": "Aerial"
    },
    {
      "id": "263592",
      "minute": "44",
      "result": "SavedShot",
      "X": "0.8059999847412109",
      "Y": "0.7630000305175781",
      "xG": "0.015284700319170952",
      "player": "Demarai Gray",
      "h_a": "h",
      "player_id": "762",
      "situation": "OpenPlay",
      "season": "2018",
      "shotType": "RightFoot",
      "match_id": "9392",
      "h_team": "Leicester",
      "a_team": "Cardiff",
      "h_goals": "0",
      "a_goals": "1",
      "date": "2018-12-29 15:00:00",
      "player_assisted": "Ben Chilwell",
      "lastAction": "Pass"
    },
    {
      "id": "263593",
      "minute": "47",
      "result": "SavedShot",
      "X": "0.8769999694824219",
      "Y": "0.3579999923706055",
      "xG": "0.07895950227975845",
      "player": "Ricardo Pereira",
      "h_a": "h",
      "player_id": "3303",
      "situation": "OpenPlay",
      "season": "2018",
      "shotType": "LeftFoot",
      "match_id": "9392",
      "h_team": "Leicester",
      "a_team": "Cardiff",
      "h_goals": "0",
      "a_goals": "1",
      "date": "2018-12-29 15:00:00",
      "player_assisted": "Jamie Vardy",
      "lastAction": "Pass"
    },
    {
      "id": "263599",
      "minute": "72",
      "result": "BlockedShot",
      "X": "0.759000015258789",
      "Y": "0.3160000038146973",
      "xG": "0.014460399746894836",
      "player": "Rachid Ghezzal",
      "h_a": "h",
      "player_id": "3276",
      "situation": "OpenPlay",
      "season": "2018",
      "shotType": "LeftFoot",
      "match_id": "9392",
      "h_team": "Leicester",
      "a_team": "Cardiff",
      "h_goals": "0",
      "a_goals": "1",
      "date": "2018-12-29 15:00:00",
      "player_assisted": "Ricardo Pereira",
      "lastAction": "Pass"
    },
    {
      "id": "263600",
      "minute": "74",
      "result": "SavedShot",
      "X": "0.885",
      "Y": "0.5",
      "xG": "0.7611690163612366",
      "player": "James Maddison",
      "h_a": "h",
      "player_id": "6818",
      "situation": "Penalty",
      "season": "2018",
      "shotType": "RightFoot",
      "match_id": "9392",
      "h_team": "Leicester",
      "a_team": "Cardiff",
      "h_goals": "0",
      "a_goals": "1",
      "date": "2018-12-29 15:00:00",
      "player_assisted": null,
      "lastAction": "Standard"
    },
    {
      "id": "263601",
      "minute": "81",
      "result": "BlockedShot",
      "X": "0.865",
      "Y": "0.3890000152587891",
      "xG": "0.07011459767818451",
      "player": "Rachid Ghezzal",
      "h_a": "h",
      "player_id": "3276",
      "situation": "OpenPlay",
      "season": "2018",
      "shotType": "RightFoot",
      "match_id": "9392",
      "h_team": "Leicester",
      "a_team": "Cardiff",
      "h_goals": "0",
      "a_goals": "1",
      "date": "2018-12-29 15:00:00",
      "player_assisted": "Wilfred Ndidi",
      "lastAction": "Chipped"
    },
    {
      "id": "263602",
      "minute": "86",
      "result": "BlockedShot",
      "X": "0.789000015258789",
      "Y": "0.345",
      "xG": "0.026673899963498116",
      "player": "Rachid Ghezzal",
      "h_a": "h",
      "player_id": "3276",
      "situation": "OpenPlay",
      "season": "2018",
      "shotType": "LeftFoot",
      "match_id": "9392",
      "h_team": "Leicester",
      "a_team": "Cardiff",
      "h_goals": "0",
      "a_goals": "1",
      "date": "2018-12-29 15:00:00",
      "player_assisted": "Ricardo Pereira",
      "lastAction": "BallTouch"
    },
    {
      "id": "263603",
      "minute": "87",
      "result": "BlockedShot",
      "X": "0.8180000305175781",
      "Y": "0.27399999618530274",
      "xG": "0.017616000026464462",
      "player": "Ricardo Pereira",
      "h_a": "h",
      "player_id": "3303",
      "situation": "FromCorner",
      "season": "2018",
      "shotType": "RightFoot",
      "match_id": "9392",
      "h_team": "Leicester",
      "a_team": "Cardiff",
      "h_goals": "0",
      "a_goals": "1",
      "date": "2018-12-29 15:00:00",
      "player_assisted": null,
      "lastAction": "None"
    }
  ],
  "a": [
    {
      "id": "263579",
      "minute": "6",
      "result": "BlockedShot",
      "X": "0.745",
      "Y": "0.40900001525878904",
      "xG": "0.016788000240921974",
      "player": "Harry Arter",
      "h_a": "a",
      "player_id": "881",
      "situation": "OpenPlay",
      "season": "2018",
      "shotType": "LeftFoot",
      "match_id": "9392",
      "h_team": "Leicester",
      "a_team": "Cardiff",
      "h_goals": "0",
      "a_goals": "1",
      "date": "2018-12-29 15:00:00",
      "player_assisted": null,
      "lastAction": "None"
    },
    {
      "id": "263580",
      "minute": "9",
      "result": "MissedShots",
      "X": "0.889000015258789",
      "Y": "0.49599998474121093",
      "xG": "0.06835409998893738",
      "player": "Sean Morrison",
      "h_a": "a",
      "player_id": "6823",
      "situation": "OpenPlay",
      "season": "2018",
      "shotType": "Head",
      "match_id": "9392",
      "h_team": "Leicester",
      "a_team": "Cardiff",
      "h_goals": "0",
      "a_goals": "1",
      "date": "2018-12-29 15:00:00",
      "player_assisted": "Aron Gunnarsson",
      "lastAction": "Cross"
    },
    {
      "id": "263585",
      "minute": "23",
      "result": "BlockedShot",
      "X": "0.9119999694824219",
      "Y": "0.5979999923706054",
      "xG": "0.08931519836187363",
      "player": "Josh Murphy",
      "h_a": "a",
      "player_id": "6828",
      "situation": "OpenPlay",
      "season": "2018",
      "shotType": "LeftFoot",
      "match_id": "9392",
      "h_team": "Leicester",
      "a_team": "Cardiff",
      "h_goals": "0",
      "a_goals": "1",
      "date": "2018-12-29 15:00:00",
      "player_assisted": null,
      "lastAction": "None"
    },
    {
      "id": "263591",
      "minute": "43",
      "result": "BlockedShot",
      "X": "0.7709999847412109",
      "Y": "0.5279999923706055",
      "xG": "0.03014189936220646",
      "player": "Junior Hoilett",
      "h_a": "a",
      "player_id": "4395",
      "situation": "OpenPlay",
      "season": "2018",
      "shotType": "LeftFoot",
      "match_id": "9392",
      "h_team": "Leicester",
      "a_team": "Cardiff",
      "h_goals": "0",
      "a_goals": "1",
      "date": "2018-12-29 15:00:00",
      "player_assisted": "Víctor Camarasa",
      "lastAction": "Pass"
    },
    {
      "id": "263594",
      "minute": "54",
      "result": "BlockedShot",
      "X": "0.7190000152587891",
      "Y": "0.36900001525878906",
      "xG": "0.03971090167760849",
      "player": "Víctor Camarasa",
      "h_a": "a",
      "player_id": "2390",
      "situation": "DirectFreekick",
      "season": "2018",
      "shotType": "RightFoot",
      "match_id": "9392",
      "h_team": "Leicester",
      "a_team": "Cardiff",
      "h_goals": "0",
      "a_goals": "1",
      "date": "2018-12-29 15:00:00",
      "player_assisted": null,
      "lastAction": "Standard"
    },
    {
      "id": "263595",
      "minute": "65",
      "result": "SavedShot",
      "X": "0.8240000152587891",
      "Y": "0.6609999847412109",
      "xG": "0.040658801794052124",
      "player": "Josh Murphy",
      "h_a": "a",
      "player_id": "6828",
      "situation": "OpenPlay",
      "season": "2018",
      "shotType": "LeftFoot",
      "match_id": "9392",
      "h_team": "Leicester",
      "a_team": "Cardiff",
      "h_goals": "0",
      "a_goals": "1",
      "date": "2018-12-29 15:00:00",
      "player_assisted": null,
      "lastAction": "BallRecovery"
    },
    {
      "id": "263596",
      "minute": "66",
      "result": "BlockedShot",
      "X": "0.745",
      "Y": "0.555",
      "xG": "0.018791500478982925",
      "player": "Junior Hoilett",
      "h_a": "a",
      "player_id": "4395",
      "situation": "OpenPlay",
      "season": "2018",
      "shotType": "RightFoot",
      "match_id": "9392",
      "h_team": "Leicester",
      "a_team": "Cardiff",
      "h_goals": "0",
      "a_goals": "1",
      "date": "2018-12-29 15:00:00",
      "player_assisted": "Víctor Camarasa",
      "lastAction": "Pass"
    },
    {
      "id": "263597",
      "minute": "66",
      "result": "MissedShots",
      "X": "0.9259999847412109",
      "Y": "0.7230000305175781",
      "xG": "0.03379340097308159",
      "player": "Josh Murphy",
      "h_a": "a",
      "player_id": "6828",
      "situation": "OpenPlay",
      "season": "2018",
      "shotType": "LeftFoot",
      "match_id": "9392",
      "h_team": "Leicester",
      "a_team": "Cardiff",
      "h_goals": "0",
      "a_goals": "1",
      "date": "2018-12-29 15:00:00",
      "player_assisted": null,
      "lastAction": "Rebound"
    },
    {
      "id": "263598",
      "minute": "70",
      "result": "MissedShots",
      "X": "0.785",
      "Y": "0.72",
      "xG": "0.016154900193214417",
      "player": "Víctor Camarasa",
      "h_a": "a",
      "player_id": "2390",
      "situation": "OpenPlay",
      "season": "2018",
      "shotType": "RightFoot",
      "match_id": "9392",
      "h_team": "Leicester",
      "a_team": "Cardiff",
      "h_goals": "0",
      "a_goals": "1",
      "date": "2018-12-29 15:00:00",
      "player_assisted": "Josh Murphy",
      "lastAction": "Pass"
    },
    {
      "id": "263604",
      "minute": "90",
      "result": "BlockedShot",
      "X": "0.7880000305175782",
      "Y": "0.35900001525878905",
      "xG": "0.019462499767541885",
      "player": "Harry Arter",
      "h_a": "a",
      "player_id": "881",
      "situation": "FromCorner",
      "season": "2018",
      "shotType": "LeftFoot",
      "match_id": "9392",
      "h_team": "Leicester",
      "a_team": "Cardiff",
      "h_goals": "0",
      "a_goals": "1",
      "date": "2018-12-29 15:00:00",
      "player_assisted": null,
      "lastAction": "None"
    },
    {
      "id": "263605",
      "minute": "91",
      "result": "Goal",
      "X": "0.769000015258789",
      "Y": "0.69",
      "xG": "0.016237599775195122",
      "player": "Víctor Camarasa",
      "h_a": "a",
      "player_id": "2390",
      "situation": "OpenPlay",
      "season": "2018",
      "shotType": "RightFoot",
      "match_id": "9392",
      "h_team": "Leicester",
      "a_team": "Cardiff",
      "h_goals": "0",
      "a_goals": "1",
      "date": "2018-12-29 15:00:00",
      "player_assisted": "Bobby Reid",
      "lastAction": "Pass"
    },
    {
      "id": "263606",
      "minute": "95",
      "result": "SavedShot",
      "X": "0.87",
      "Y": "0.42200000762939455",
      "xG": "0.10443799942731857",
      "player": "Kadeem Harris",
      "h_a": "a",
      "player_id": "7120",
      "situation": "OpenPlay",
      "season": "2018",
      "shotType": "RightFoot",
      "match_id": "9392",
      "h_team": "Leicester",
      "a_team": "Cardiff",
      "h_goals": "0",
      "a_goals": "1",
      "date": "2018-12-29 15:00:00",
      "player_assisted": "Callum Paterson",
      "lastAction": "Pass"
    }
  ]
}