{
  "h": [
    {
      "id": "590795",
      "minute": "15",
      "result": "MissedShots",
      "X": "0.899000015258789",
      "Y": "0.49400001525878906",
      "xG": "0.04854709655046463",
      "player": "Eddie Nketiah",
      "h_a": "h",
      "player_id": "6482",
      "situation": "OpenPlay",
      "season": "2024",
      "shotType": "Head",
      "match_id": "26636",
      "h_team": "Crystal Palace",
      "a_team": "Leicester",
      "h_goals": "2",
      "a_goals": "2",
      "date": "2024-09-14 14:00:00",
      "player_assisted": "Tyrick Mitchell",
      "lastAction": "Aerial"
    },
    {
      "id": "590796",
      "minute": "17",
      "result": "BlockedShot",
      "X": "0.879000015258789",
      "Y": "0.4",
      "xG": "0.32204240560531616",
      "player": "Daniel Mu単oz",
      "h_a": "h",
      "player_id": "12408",
      "situation": "OpenPlay",
      "season": "2024",
      "shotType": "RightFoot",
      "match_id": "26636",
      "h_team": "Crystal Palace",
      "a_team": "Leicester",
      "h_goals": "2",
      "a_goals": "2",
      "date": "2024-09-14 14:00:00",
      "player_assisted": "Eberechi Eze",
      "lastAction": "Pass"
    },
    {
      "id": "590797",
      "minute": "17",
      "result": "BlockedShot",
      "X": "0.9130000305175782",
      "Y": "0.29700000762939455",
      "xG": "0.03961462154984474",
      "player": "Eddie Nketiah",
      "h_a": "h",
      "player_id": "6482",
      "situation": "OpenPlay",
      "season": "2024",
      "shotType": "LeftFoot",
      "match_id": "26636",
      "h_team": "Crystal Palace",
      "a_team": "Leicester",
      "h_goals": "2",
      "a_goals": "2",
      "date": "2024-09-14 14:00:00",
      "player_assisted": "Daniel Mu単oz",
      "lastAction": "Rebound"
    },
    {
      "id": "590798",
      "minute": "18",
      "result": "BlockedShot",
      "X": "0.9080000305175782",
      "Y": "0.35400001525878905",
      "xG": "0.08938568085432053",
      "player": "Jean-Philippe Mateta",
      "h_a": "h",
      "player_id": "5735",
      "situation": "OpenPlay",
      "season": "2024",
      "shotType": "RightFoot",
      "match_id": "26636",
      "h_team": "Crystal Palace",
      "a_team": "Leicester",
      "h_goals": "2",
      "a_goals": "2",
      "date": "2024-09-14 14:00:00",
      "player_assisted": "Eberechi Eze",
      "lastAction": "Pass"
    },
    {
      "id": "590799",
      "minute": "18",
      "result": "SavedShot",
      "X": "0.8540000152587891",
      "Y": "0.38799999237060545",
      "xG": "0.07497850060462952",
      "player": "Eddie Nketiah",
      "h_a": "h",
      "player_id": "6482",
      "situation": "OpenPlay",
      "season": "2024",
      "shotType": "LeftFoot",
      "match_id": "26636",
      "h_team": "Crystal Palace",
      "a_team": "Leicester",
      "h_goals": "2",
      "a_goals": "2",
      "date": "2024-09-14 14:00:00",
      "player_assisted": "Adam Wharton",
      "lastAction": "Pass"
    },
    {
      "id": "590803",
      "minute": "27",
      "result": "MissedShots",
      "X": "0.7669999694824219",
      "Y": "0.49700000762939456",
      "xG": "0.026361901313066483",
      "player": "Cheick Oumar Doucoure",
      "h_a": "h",
      "player_id": "8666",
      "situation": "OpenPlay",
      "season": "2024",
      "shotType": "RightFoot",
      "match_id": "26636",
      "h_team": "Crystal Palace",
      "a_team": "Leicester",
      "h_goals": "2",
      "a_goals": "2",
      "date": "2024-09-14 14:00:00",
      "player_assisted": "Eberechi Eze",
      "lastAction": "Pass"
    },
    {
      "id": "590804",
      "minute": "30",
      "result": "BlockedShot",
      "X": "0.885",
      "Y": "0.639000015258789",
      "xG": "0.06661520153284073",
      "player": "Eddie Nketiah",
      "h_a": "h",
      "player_id": "6482",
      "situation": "OpenPlay",
      "season": "2024",
      "shotType": "RightFoot",
      "match_id": "26636",
      "h_team": "Crystal Palace",
      "a_team": "Leicester",
      "h_goals": "2",
      "a_goals": "2",
      "date": "2024-09-14 14:00:00",
      "player_assisted": "Tyrick Mitchell",
      "lastAction": "Pass"
    },
    {
      "id": "590805",
      "minute": "32",
      "result": "BlockedShot",
      "X": "0.8430000305175781",
      "Y": "0.44",
      "xG": "0.02383996546268463",
      "player": "Daniel Mu単oz",
      "h_a": "h",
      "player_id": "12408",
      "situation": "FromCorner",
      "season": "2024",
      "shotType": "RightFoot",
      "match_id": "26636",
      "h_team": "Crystal Palace",
      "a_team": "Leicester",
      "h_goals": "2",
      "a_goals": "2",
      "date": "2024-09-14 14:00:00",
      "player_assisted": "Maxence Lacroix",
      "lastAction": "HeadPass"
    },
    {
      "id": "590806",
      "minute": "32",
      "result": "MissedShots",
      "X": "0.919000015258789",
      "Y": "0.46700000762939453",
      "xG": "0.13234081864356995",
      "player": "Eddie Nketiah",
      "h_a": "h",
      "player_id": "6482",
      "situation": "FromCorner",
      "season": "2024",
      "shotType": "RightFoot",
      "match_id": "26636",
      "h_team": "Crystal Palace",
      "a_team": "Leicester",
      "h_goals": "2",
      "a_goals": "2",
      "date": "2024-09-14 14:00:00",
      "player_assisted": null,
      "lastAction": "Rebound"
    },
    {
      "id": "590807",
      "minute": "34",
      "result": "MissedShots",
      "X": "0.9480000305175781",
      "Y": "0.6079999923706054",
      "xG": "0.34781399369239807",
      "player": "Eberechi Eze",
      "h_a": "h",
      "player_id": "8706",
      "situation": "OpenPlay",
      "season": "2024",
      "shotType": "RightFoot",
      "match_id": "26636",
      "h_team": "Crystal Palace",
      "a_team": "Leicester",
      "h_goals": "2",
      "a_goals": "2",
      "date": "2024-09-14 14:00:00",
      "player_assisted": "Tyrick Mitchell",
      "lastAction": "TakeOn"
    },
    {
      "id": "590810",
      "minute": "46",
      "result": "Goal",
      "X": "0.9680000305175781",
      "Y": "0.5359999847412109",
      "xG": "0.5914250612258911",
      "player": "Jean-Philippe Mateta",
      "h_a": "h",
      "player_id": "5735",
      "situation": "OpenPlay",
      "season": "2024",
      "shotType": "RightFoot",
      "match_id": "26636",
      "h_team": "Crystal Palace",
      "a_team": "Leicester",
      "h_goals": "2",
      "a_goals": "2",
      "date": "2024-09-14 14:00:00",
      "player_assisted": "Tyrick Mitchell",
      "lastAction": "Cross"
    },
    {
      "id": "590813",
      "minute": "65",
      "result": "BlockedShot",
      "X": "0.7609999847412109",
      "Y": "0.43599998474121093",
      "xG": "0.0255703404545784",
      "player": "Daichi Kamada",
      "h_a": "h",
      "player_id": "6145",
      "situation": "OpenPlay",
      "season": "2024",
      "shotType": "RightFoot",
      "match_id": "26636",
      "h_team": "Crystal Palace",
      "a_team": "Leicester",
      "h_goals": "2",
      "a_goals": "2",
      "date": "2024-09-14 14:00:00",
      "player_assisted": "Adam Wharton",
      "lastAction": "Pass"
    },
    {
      "id": "590814",
      "minute": "67",
      "result": "MissedShots",
      "X": "0.8819999694824219",
      "Y": "0.3270000076293945",
      "xG": "0.048787280917167664",
      "player": "Eddie Nketiah",
      "h_a": "h",
      "player_id": "6482",
      "situation": "OpenPlay",
      "season": "2024",
      "shotType": "RightFoot",
      "match_id": "26636",
      "h_team": "Crystal Palace",
      "a_team": "Leicester",
      "h_goals": "2",
      "a_goals": "2",
      "date": "2024-09-14 14:00:00",
      "player_assisted": "Daniel Mu単oz",
      "lastAction": "BallTouch"
    },
    {
      "id": "590815",
      "minute": "74",
      "result": "BlockedShot",
      "X": "0.904000015258789",
      "Y": "0.5359999847412109",
      "xG": "0.10448204725980759",
      "player": "Eberechi Eze",
      "h_a": "h",
      "player_id": "8706",
      "situation": "OpenPlay",
      "season": "2024",
      "shotType": "LeftFoot",
      "match_id": "26636",
      "h_team": "Crystal Palace",
      "a_team": "Leicester",
      "h_goals": "2",
      "a_goals": "2",
      "date": "2024-09-14 14:00:00",
      "player_assisted": "Eddie Nketiah",
      "lastAction": "Pass"
    },
    {
      "id": "590816",
      "minute": "79",
      "result": "BlockedShot",
      "X": "0.7919999694824219",
      "Y": "0.754000015258789",
      "xG": "0.04875122755765915",
      "player": "Eberechi Eze",
      "h_a": "h",
      "player_id": "8706",
      "situation": "DirectFreekick",
      "season": "2024",
      "shotType": "RightFoot",
      "match_id": "26636",
      "h_team": "Crystal Palace",
      "a_team": "Leicester",
      "h_goals": "2",
      "a_goals": "2",
      "date": "2024-09-14 14:00:00",
      "player_assisted": null,
      "lastAction": "Standard"
    },
    {
      "id": "590818",
      "minute": "83",
      "result": "SavedShot",
      "X": "0.879000015258789",
      "Y": "0.7330000305175781",
      "xG": "0.031843822449445724",
      "player": "Tyrick Mitchell",
      "h_a": "h",
      "player_id": "8214",
      "situation": "OpenPlay",
      "season": "2024",
      "shotType": "LeftFoot",
      "match_id": "26636",
      "h_team": "Crystal Palace",
      "a_team": "Leicester",
      "h_goals": "2",
      "a_goals": "2",
      "date": "2024-09-14 14:00:00",
      "player_assisted": null,
      "lastAction": "None"
    },
    {
      "id": "590819",
      "minute": "84",
      "result": "BlockedShot",
      "X": "0.905",
      "Y": "0.615",
      "xG": "0.06907149404287338",
      "player": "Daichi Kamada",
      "h_a": "h",
      "player_id": "6145",
      "situation": "OpenPlay",
      "season": "2024",
      "shotType": "LeftFoot",
      "match_id": "26636",
      "h_team": "Crystal Palace",
      "a_team": "Leicester",
      "h_goals": "2",
      "a_goals": "2",
      "date": "2024-09-14 14:00:00",
      "player_assisted": null,
      "lastAction": "Dispossessed"
    },
    {
      "id": "590820",
      "minute": "85",
      "result": "BlockedShot",
      "X": "0.8040000152587891",
      "Y": "0.3890000152587891",
      "xG": "0.03502091392874718",
      "player": "Ismaila Sarr",
      "h_a": "h",
      "player_id": "5675",
      "situation": "OpenPlay",
      "season": "2024",
      "shotType": "LeftFoot",
      "match_id": "26636",
      "h_team": "Crystal Palace",
      "a_team": "Leicester",
      "h_goals": "2",
      "a_goals": "2",
      "date": "2024-09-14 14:00:00",
      "player_assisted": null,
      "lastAction": "None"
    },
    {
      "id": "590821",
      "minute": "86",
      "result": "MissedShots",
      "X": "0.8919999694824219",
      "Y": "0.5840000152587891",
      "xG": "0.015411007218062878",
      "player": "Jean-Philippe Mateta",
      "h_a": "h",
      "player_id": "5735",
      "situation": "FromCorner",
      "season": "2024",
      "shotType": "Head",
      "match_id": "26636",
      "h_team": "Crystal Palace",
      "a_team": "Leicester",
      "h_goals": "2",
      "a_goals": "2",
      "date": "2024-09-14 14:00:00",
      "player_assisted": "Marc Guehi",
      "lastAction": "Aerial"
    },
    {
      "id": "590822",
      "minute": "91",
      "result": "Goal",
      "X": "0.885",
      "Y": "0.5",
      "xG": "0.7611688375473022",
      "player": "Jean-Philippe Mateta",
      "h_a": "h",
      "player_id": "5735",
      "situation": "Penalty",
      "season": "2024",
      "shotType": "RightFoot",
      "match_id": "26636",
      "h_team": "Crystal Palace",
      "a_team": "Leicester",
      "h_goals": "2",
      "a_goals": "2",
      "date": "2024-09-14 14:00:00",
      "player_assisted": null,
      "lastAction": "Standard"
    }
  ],
  "a": [
    {
      "id": "590794",
      "minute": "4",
      "result": "MissedShots",
      "X": "0.914000015258789",
      "Y": "0.37400001525878906",
      "xG": "0.30705711245536804",
      "player": "Jordan Ayew",
      "h_a": "a",
      "player_id": "672",
      "situation": "OpenPlay",
      "season": "2024",
      "shotType": "RightFoot",
      "match_id": "26636",
      "h_team": "Crystal Palace",
      "a_team": "Leicester",
      "h_goals": "2",
      "a_goals": "2",
      "date": "2024-09-14 14:00:00",
      "player_assisted": "Wilfred Ndidi",
      "lastAction": "Chipped"
    },
    {
      "id": "590800",
      "minute": "20",
      "result": "Goal",
      "X": "0.955",
      "Y": "0.34200000762939453",
      "xG": "0.5000195503234863",
      "player": "Jamie Vardy",
      "h_a": "a",
      "player_id": "755",
      "situation": "OpenPlay",
      "season": "2024",
      "shotType": "RightFoot",
      "match_id": "26636",
      "h_team": "Crystal Palace",
      "a_team": "Leicester",
      "h_goals": "2",
      "a_goals": "2",
      "date": "2024-09-14 14:00:00",
      "player_assisted": "Wilfred Ndidi",
      "lastAction": "TakeOn"
    },
    {
      "id": "590801",
      "minute": "23",
      "result": "BlockedShot",
      "X": "0.899000015258789",
      "Y": "0.6419999694824219",
      "xG": "0.10051091760396957",
      "player": "Stephy Mavididi",
      "h_a": "a",
      "player_id": "7484",
      "situation": "OpenPlay",
      "season": "2024",
      "shotType": "LeftFoot",
      "match_id": "26636",
      "h_team": "Crystal Palace",
      "a_team": "Leicester",
      "h_goals": "2",
      "a_goals": "2",
      "date": "2024-09-14 14:00:00",
      "player_assisted": "Oliver Skipp",
      "lastAction": "Pass"
    },
    {
      "id": "590802",
      "minute": "24",
      "result": "SavedShot",
      "X": "0.8819999694824219",
      "Y": "0.5779999923706055",
      "xG": "0.02058715745806694",
      "player": "Caleb Okoli",
      "h_a": "a",
      "player_id": "7333",
      "situation": "FromCorner",
      "season": "2024",
      "shotType": "Head",
      "match_id": "26636",
      "h_team": "Crystal Palace",
      "a_team": "Leicester",
      "h_goals": "2",
      "a_goals": "2",
      "date": "2024-09-14 14:00:00",
      "player_assisted": "Victor Kristiansen",
      "lastAction": "Cross"
    },
    {
      "id": "590808",
      "minute": "44",
      "result": "MissedShots",
      "X": "0.9159999847412109",
      "Y": "0.6519999694824219",
      "xG": "0.10246366262435913",
      "player": "Stephy Mavididi",
      "h_a": "a",
      "player_id": "7484",
      "situation": "OpenPlay",
      "season": "2024",
      "shotType": "LeftFoot",
      "match_id": "26636",
      "h_team": "Crystal Palace",
      "a_team": "Leicester",
      "h_goals": "2",
      "a_goals": "2",
      "date": "2024-09-14 14:00:00",
      "player_assisted": "Jamie Vardy",
      "lastAction": "Pass"
    },
    {
      "id": "590809",
      "minute": "45",
      "result": "Goal",
      "X": "0.924000015258789",
      "Y": "0.5179999923706055",
      "xG": "0.5542885661125183",
      "player": "Stephy Mavididi",
      "h_a": "a",
      "player_id": "7484",
      "situation": "OpenPlay",
      "season": "2024",
      "shotType": "RightFoot",
      "match_id": "26636",
      "h_team": "Crystal Palace",
      "a_team": "Leicester",
      "h_goals": "2",
      "a_goals": "2",
      "date": "2024-09-14 14:00:00",
      "player_assisted": "Wilfred Ndidi",
      "lastAction": "Pass"
    },
    {
      "id": "590811",
      "minute": "55",
      "result": "MissedShots",
      "X": "0.7959999847412109",
      "Y": "0.39799999237060546",
      "xG": "0.04702083021402359",
      "player": "James Justin",
      "h_a": "a",
      "player_id": "7753",
      "situation": "OpenPlay",
      "season": "2024",
      "shotType": "RightFoot",
      "match_id": "26636",
      "h_team": "Crystal Palace",
      "a_team": "Leicester",
      "h_goals": "2",
      "a_goals": "2",
      "date": "2024-09-14 14:00:00",
      "player_assisted": "Wilfred Ndidi",
      "lastAction": "Pass"
    },
    {
      "id": "590812",
      "minute": "60",
      "result": "SavedShot",
      "X": "0.8619999694824219",
      "Y": "0.46700000762939453",
      "xG": "0.009671765379607677",
      "player": "Jordan Ayew",
      "h_a": "a",
      "player_id": "672",
      "situation": "SetPiece",
      "season": "2024",
      "shotType": "Head",
      "match_id": "26636",
      "h_team": "Crystal Palace",
      "a_team": "Leicester",
      "h_goals": "2",
      "a_goals": "2",
      "date": "2024-09-14 14:00:00",
      "player_assisted": "Victor Kristiansen",
      "lastAction": "Aerial"
    },
    {
      "id": "590817",
      "minute": "81",
      "result": "MissedShots",
      "X": "0.41700000762939454",
      "Y": "0.6419999694824219",
      "xG": "0.010250847786664963",
      "player": "Abdul Fatawu",
      "h_a": "a",
      "player_id": "12911",
      "situation": "OpenPlay",
      "season": "2024",
      "shotType": "LeftFoot",
      "match_id": "26636",
      "h_team": "Crystal Palace",
      "a_team": "Leicester",
      "h_goals": "2",
      "a_goals": "2",
      "date": "2024-09-14 14:00:00",
      "player_assisted": "Oliver Skipp",
      "lastAction": "BallRecovery"
    }
  ]
}