{
  "h": [
    {
      "id": "274976",
      "minute": "3",
      "result": "BlockedShot",
      "X": "0.794000015258789",
      "Y": "0.34299999237060547",
      "xG": "0.02553039975464344",
      "player": "Andreas Pereira",
      "h_a": "h",
      "player_id": "922",
      "situation": "FromCorner",
      "season": "2018",
      "shotType": "RightFoot",
      "match_id": "9432",
      "h_team": "Manchester United",
      "a_team": "Burnley",
      "h_goals": "2",
      "a_goals": "2",
      "date": "2019-01-29 20:00:00",
      "player_assisted": "Ashley Young",
      "lastAction": "Pass"
    },
    {
      "id": "274977",
      "minute": "4",
      "result": "BlockedShot",
      "X": "0.884000015258789",
      "Y": "0.39799999237060546",
      "xG": "0.04565399885177612",
      "player": "Marcus Rashford",
      "h_a": "h",
      "player_id": "556",
      "situation": "FromCorner",
      "season": "2018",
      "shotType": "RightFoot",
      "match_id": "9432",
      "h_team": "Manchester United",
      "a_team": "Burnley",
      "h_goals": "2",
      "a_goals": "2",
      "date": "2019-01-29 20:00:00",
      "player_assisted": "Luke Shaw",
      "lastAction": "Cross"
    },
    {
      "id": "274979",
      "minute": "8",
      "result": "MissedShots",
      "X": "0.9030000305175782",
      "Y": "0.544000015258789",
      "xG": "0.5565720200538635",
      "player": "Marcus Rashford",
      "h_a": "h",
      "player_id": "556",
      "situation": "OpenPlay",
      "season": "2018",
      "shotType": "RightFoot",
      "match_id": "9432",
      "h_team": "Manchester United",
      "a_team": "Burnley",
      "h_goals": "2",
      "a_goals": "2",
      "date": "2019-01-29 20:00:00",
      "player_assisted": "Romelu Lukaku",
      "lastAction": "Pass"
    },
    {
      "id": "274982",
      "minute": "19",
      "result": "MissedShots",
      "X": "0.765",
      "Y": "0.595999984741211",
      "xG": "0.014225699938833714",
      "player": "Luke Shaw",
      "h_a": "h",
      "player_id": "1006",
      "situation": "FromCorner",
      "season": "2018",
      "shotType": "LeftFoot",
      "match_id": "9432",
      "h_team": "Manchester United",
      "a_team": "Burnley",
      "h_goals": "2",
      "a_goals": "2",
      "date": "2019-01-29 20:00:00",
      "player_assisted": null,
      "lastAction": "Aerial"
    },
    {
      "id": "274983",
      "minute": "33",
      "result": "BlockedShot",
      "X": "0.805",
      "Y": "0.62",
      "xG": "0.0364518016576767",
      "player": "Luke Shaw",
      "h_a": "h",
      "player_id": "1006",
      "situation": "OpenPlay",
      "season": "2018",
      "shotType": "RightFoot",
      "match_id": "9432",
      "h_team": "Manchester United",
      "a_team": "Burnley",
      "h_goals": "2",
      "a_goals": "2",
      "date": "2019-01-29 20:00:00",
      "player_assisted": null,
      "lastAction": "None"
    },
    {
      "id": "274984",
      "minute": "34",
      "result": "MissedShots",
      "X": "0.8980000305175782",
      "Y": "0.54",
      "xG": "0.04369800165295601",
      "player": "Victor Lindelöf",
      "h_a": "h",
      "player_id": "6080",
      "situation": "FromCorner",
      "season": "2018",
      "shotType": "Head",
      "match_id": "9432",
      "h_team": "Manchester United",
      "a_team": "Burnley",
      "h_goals": "2",
      "a_goals": "2",
      "date": "2019-01-29 20:00:00",
      "player_assisted": "Phil Jones",
      "lastAction": "Chipped"
    },
    {
      "id": "274985",
      "minute": "40",
      "result": "MissedShots",
      "X": "0.7759999847412109",
      "Y": "0.35200000762939454",
      "xG": "0.023483000695705414",
      "player": "Juan Mata",
      "h_a": "h",
      "player_id": "554",
      "situation": "OpenPlay",
      "season": "2018",
      "shotType": "LeftFoot",
      "match_id": "9432",
      "h_team": "Manchester United",
      "a_team": "Burnley",
      "h_goals": "2",
      "a_goals": "2",
      "date": "2019-01-29 20:00:00",
      "player_assisted": "Andreas Pereira",
      "lastAction": "Pass"
    },
    {
      "id": "274986",
      "minute": "43",
      "result": "MissedShots",
      "X": "0.775",
      "Y": "0.30700000762939456",
      "xG": "0.02026209980249405",
      "player": "Ashley Young",
      "h_a": "h",
      "player_id": "631",
      "situation": "OpenPlay",
      "season": "2018",
      "shotType": "RightFoot",
      "match_id": "9432",
      "h_team": "Manchester United",
      "a_team": "Burnley",
      "h_goals": "2",
      "a_goals": "2",
      "date": "2019-01-29 20:00:00",
      "player_assisted": "Nemanja Matic",
      "lastAction": "Pass"
    },
    {
      "id": "274987",
      "minute": "46",
      "result": "SavedShot",
      "X": "0.825",
      "Y": "0.44799999237060545",
      "xG": "0.06136859953403473",
      "player": "Juan Mata",
      "h_a": "h",
      "player_id": "554",
      "situation": "OpenPlay",
      "season": "2018",
      "shotType": "LeftFoot",
      "match_id": "9432",
      "h_team": "Manchester United",
      "a_team": "Burnley",
      "h_goals": "2",
      "a_goals": "2",
      "date": "2019-01-29 20:00:00",
      "player_assisted": null,
      "lastAction": "Dispossessed"
    },
    {
      "id": "274988",
      "minute": "47",
      "result": "MissedShots",
      "X": "0.915",
      "Y": "0.524000015258789",
      "xG": "0.12246300280094147",
      "player": "Paul Pogba",
      "h_a": "h",
      "player_id": "1740",
      "situation": "OpenPlay",
      "season": "2018",
      "shotType": "Head",
      "match_id": "9432",
      "h_team": "Manchester United",
      "a_team": "Burnley",
      "h_goals": "2",
      "a_goals": "2",
      "date": "2019-01-29 20:00:00",
      "player_assisted": "Juan Mata",
      "lastAction": "Cross"
    },
    {
      "id": "274989",
      "minute": "49",
      "result": "SavedShot",
      "X": "0.764000015258789",
      "Y": "0.649000015258789",
      "xG": "0.02149900048971176",
      "player": "Paul Pogba",
      "h_a": "h",
      "player_id": "1740",
      "situation": "OpenPlay",
      "season": "2018",
      "shotType": "RightFoot",
      "match_id": "9432",
      "h_team": "Manchester United",
      "a_team": "Burnley",
      "h_goals": "2",
      "a_goals": "2",
      "date": "2019-01-29 20:00:00",
      "player_assisted": "Luke Shaw",
      "lastAction": "Pass"
    },
    {
      "id": "274991",
      "minute": "52",
      "result": "SavedShot",
      "X": "0.7809999847412109",
      "Y": "0.46900001525878904",
      "xG": "0.03381609916687012",
      "player": "Marcus Rashford",
      "h_a": "h",
      "player_id": "556",
      "situation": "OpenPlay",
      "season": "2018",
      "shotType": "RightFoot",
      "match_id": "9432",
      "h_team": "Manchester United",
      "a_team": "Burnley",
      "h_goals": "2",
      "a_goals": "2",
      "date": "2019-01-29 20:00:00",
      "player_assisted": "Juan Mata",
      "lastAction": "Pass"
    },
    {
      "id": "274992",
      "minute": "53",
      "result": "MissedShots",
      "X": "0.8159999847412109",
      "Y": "0.6790000152587891",
      "xG": "0.03308140113949776",
      "player": "Marcus Rashford",
      "h_a": "h",
      "player_id": "556",
      "situation": "OpenPlay",
      "season": "2018",
      "shotType": "LeftFoot",
      "match_id": "9432",
      "h_team": "Manchester United",
      "a_team": "Burnley",
      "h_goals": "2",
      "a_goals": "2",
      "date": "2019-01-29 20:00:00",
      "player_assisted": "Paul Pogba",
      "lastAction": "Pass"
    },
    {
      "id": "274993",
      "minute": "55",
      "result": "MissedShots",
      "X": "0.8859999847412109",
      "Y": "0.6880000305175781",
      "xG": "0.035954300314188004",
      "player": "Luke Shaw",
      "h_a": "h",
      "player_id": "1006",
      "situation": "FromCorner",
      "season": "2018",
      "shotType": "LeftFoot",
      "match_id": "9432",
      "h_team": "Manchester United",
      "a_team": "Burnley",
      "h_goals": "2",
      "a_goals": "2",
      "date": "2019-01-29 20:00:00",
      "player_assisted": null,
      "lastAction": "None"
    },
    {
      "id": "274994",
      "minute": "55",
      "result": "MissedShots",
      "X": "0.93",
      "Y": "0.49900001525878906",
      "xG": "0.1191750019788742",
      "player": "Paul Pogba",
      "h_a": "h",
      "player_id": "1740",
      "situation": "FromCorner",
      "season": "2018",
      "shotType": "LeftFoot",
      "match_id": "9432",
      "h_team": "Manchester United",
      "a_team": "Burnley",
      "h_goals": "2",
      "a_goals": "2",
      "date": "2019-01-29 20:00:00",
      "player_assisted": "Luke Shaw",
      "lastAction": "None"
    },
    {
      "id": "274996",
      "minute": "57",
      "result": "BlockedShot",
      "X": "0.8919999694824219",
      "Y": "0.34200000762939453",
      "xG": "0.09716960042715073",
      "player": "Romelu Lukaku",
      "h_a": "h",
      "player_id": "594",
      "situation": "OpenPlay",
      "season": "2018",
      "shotType": "RightFoot",
      "match_id": "9432",
      "h_team": "Manchester United",
      "a_team": "Burnley",
      "h_goals": "2",
      "a_goals": "2",
      "date": "2019-01-29 20:00:00",
      "player_assisted": "Marcus Rashford",
      "lastAction": "Pass"
    },
    {
      "id": "274997",
      "minute": "58",
      "result": "BlockedShot",
      "X": "0.7219999694824218",
      "Y": "0.52",
      "xG": "0.014259399846196175",
      "player": "Nemanja Matic",
      "h_a": "h",
      "player_id": "697",
      "situation": "FromCorner",
      "season": "2018",
      "shotType": "LeftFoot",
      "match_id": "9432",
      "h_team": "Manchester United",
      "a_team": "Burnley",
      "h_goals": "2",
      "a_goals": "2",
      "date": "2019-01-29 20:00:00",
      "player_assisted": null,
      "lastAction": "None"
    },
    {
      "id": "274998",
      "minute": "65",
      "result": "SavedShot",
      "X": "0.9580000305175781",
      "Y": "0.4570000076293945",
      "xG": "0.11823900043964386",
      "player": "Romelu Lukaku",
      "h_a": "h",
      "player_id": "594",
      "situation": "OpenPlay",
      "season": "2018",
      "shotType": "RightFoot",
      "match_id": "9432",
      "h_team": "Manchester United",
      "a_team": "Burnley",
      "h_goals": "2",
      "a_goals": "2",
      "date": "2019-01-29 20:00:00",
      "player_assisted": "Ashley Young",
      "lastAction": "Cross"
    },
    {
      "id": "274999",
      "minute": "66",
      "result": "MissedShots",
      "X": "0.7819999694824219",
      "Y": "0.33299999237060546",
      "xG": "0.02069910056889057",
      "player": "Nemanja Matic",
      "h_a": "h",
      "player_id": "697",
      "situation": "FromCorner",
      "season": "2018",
      "shotType": "LeftFoot",
      "match_id": "9432",
      "h_team": "Manchester United",
      "a_team": "Burnley",
      "h_goals": "2",
      "a_goals": "2",
      "date": "2019-01-29 20:00:00",
      "player_assisted": "Juan Mata",
      "lastAction": "Pass"
    },
    {
      "id": "275000",
      "minute": "68",
      "result": "BlockedShot",
      "X": "0.8859999847412109",
      "Y": "0.48700000762939455",
      "xG": "0.01560330018401146",
      "player": "Victor Lindelöf",
      "h_a": "h",
      "player_id": "6080",
      "situation": "FromCorner",
      "season": "2018",
      "shotType": "Head",
      "match_id": "9432",
      "h_team": "Manchester United",
      "a_team": "Burnley",
      "h_goals": "2",
      "a_goals": "2",
      "date": "2019-01-29 20:00:00",
      "player_assisted": "Luke Shaw",
      "lastAction": "Aerial"
    },
    {
      "id": "275001",
      "minute": "69",
      "result": "MissedShots",
      "X": "0.9630000305175781",
      "Y": "0.445",
      "xG": "0.12876899540424347",
      "player": "Paul Pogba",
      "h_a": "h",
      "player_id": "1740",
      "situation": "OpenPlay",
      "season": "2018",
      "shotType": "Head",
      "match_id": "9432",
      "h_team": "Manchester United",
      "a_team": "Burnley",
      "h_goals": "2",
      "a_goals": "2",
      "date": "2019-01-29 20:00:00",
      "player_assisted": "Alexis Sánchez",
      "lastAction": "Cross"
    },
    {
      "id": "275002",
      "minute": "75",
      "result": "BlockedShot",
      "X": "0.7830000305175782",
      "Y": "0.5270000076293946",
      "xG": "0.09890919923782349",
      "player": "Juan Mata",
      "h_a": "h",
      "player_id": "554",
      "situation": "DirectFreekick",
      "season": "2018",
      "shotType": "LeftFoot",
      "match_id": "9432",
      "h_team": "Manchester United",
      "a_team": "Burnley",
      "h_goals": "2",
      "a_goals": "2",
      "date": "2019-01-29 20:00:00",
      "player_assisted": null,
      "lastAction": "Standard"
    },
    {
      "id": "275004",
      "minute": "83",
      "result": "SavedShot",
      "X": "0.935",
      "Y": "0.595999984741211",
      "xG": "0.039965398609638214",
      "player": "Marcus Rashford",
      "h_a": "h",
      "player_id": "556",
      "situation": "OpenPlay",
      "season": "2018",
      "shotType": "Head",
      "match_id": "9432",
      "h_team": "Manchester United",
      "a_team": "Burnley",
      "h_goals": "2",
      "a_goals": "2",
      "date": "2019-01-29 20:00:00",
      "player_assisted": "Paul Pogba",
      "lastAction": "Chipped"
    },
    {
      "id": "275005",
      "minute": "86",
      "result": "Goal",
      "X": "0.885",
      "Y": "0.5",
      "xG": "0.7611690163612366",
      "player": "Paul Pogba",
      "h_a": "h",
      "player_id": "1740",
      "situation": "Penalty",
      "season": "2018",
      "shotType": "RightFoot",
      "match_id": "9432",
      "h_team": "Manchester United",
      "a_team": "Burnley",
      "h_goals": "2",
      "a_goals": "2",
      "date": "2019-01-29 20:00:00",
      "player_assisted": null,
      "lastAction": "Standard"
    },
    {
      "id": "275006",
      "minute": "89",
      "result": "SavedShot",
      "X": "0.8180000305175781",
      "Y": "0.36700000762939455",
      "xG": "0.04254529997706413",
      "player": "Paul Pogba",
      "h_a": "h",
      "player_id": "1740",
      "situation": "OpenPlay",
      "season": "2018",
      "shotType": "RightFoot",
      "match_id": "9432",
      "h_team": "Manchester United",
      "a_team": "Burnley",
      "h_goals": "2",
      "a_goals": "2",
      "date": "2019-01-29 20:00:00",
      "player_assisted": "Juan Mata",
      "lastAction": "Pass"
    },
    {
      "id": "275007",
      "minute": "91",
      "result": "SavedShot",
      "X": "0.9309999847412109",
      "Y": "0.5270000076293946",
      "xG": "0.08238519728183746",
      "player": "Alexis Sánchez",
      "h_a": "h",
      "player_id": "498",
      "situation": "FromCorner",
      "season": "2018",
      "shotType": "Head",
      "match_id": "9432",
      "h_team": "Manchester United",
      "a_team": "Burnley",
      "h_goals": "2",
      "a_goals": "2",
      "date": "2019-01-29 20:00:00",
      "player_assisted": "Ashley Young",
      "lastAction": "Chipped"
    },
    {
      "id": "275008",
      "minute": "91",
      "result": "Goal",
      "X": "0.975999984741211",
      "Y": "0.5690000152587891",
      "xG": "0.5392659902572632",
      "player": "Victor Lindelöf",
      "h_a": "h",
      "player_id": "6080",
      "situation": "FromCorner",
      "season": "2018",
      "shotType": "LeftFoot",
      "match_id": "9432",
      "h_team": "Manchester United",
      "a_team": "Burnley",
      "h_goals": "2",
      "a_goals": "2",
      "date": "2019-01-29 20:00:00",
      "player_assisted": null,
      "lastAction": "Rebound"
    },
    {
      "id": "275009",
      "minute": "93",
      "result": "BlockedShot",
      "X": "0.8859999847412109",
      "Y": "0.4929999923706055",
      "xG": "0.12638400495052338",
      "player": "Paul Pogba",
      "h_a": "h",
      "player_id": "1740",
      "situation": "OpenPlay",
      "season": "2018",
      "shotType": "RightFoot",
      "match_id": "9432",
      "h_team": "Manchester United",
      "a_team": "Burnley",
      "h_goals": "2",
      "a_goals": "2",
      "date": "2019-01-29 20:00:00",
      "player_assisted": "Marcus Rashford",
      "lastAction": "Pass"
    }
  ],
  "a": [
    {
      "id": "274978",
      "minute": "6",
      "result": "SavedShot",
      "X": "0.8080000305175781",
      "Y": "0.3509999847412109",
      "xG": "0.03516269847750664",
      "player": "Chris Wood",
      "h_a": "a",
      "player_id": "4456",
      "situation": "OpenPlay",
      "season": "2018",
      "shotType": "RightFoot",
      "match_id": "9432",
      "h_team": "Manchester United",
      "a_team": "Burnley",
      "h_goals": "2",
      "a_goals": "2",
      "date": "2019-01-29 20:00:00",
      "player_assisted": "Ashley Barnes",
      "lastAction": "BallTouch"
    },
    {
      "id": "274980",
      "minute": "10",
      "result": "BlockedShot",
      "X": "0.7659999847412109",
      "Y": "0.6469999694824219",
      "xG": "0.020423099398612976",
      "player": "Dwight McNeil",
      "h_a": "a",
      "player_id": "6756",
      "situation": "OpenPlay",
      "season": "2018",
      "shotType": "LeftFoot",
      "match_id": "9432",
      "h_team": "Manchester United",
      "a_team": "Burnley",
      "h_goals": "2",
      "a_goals": "2",
      "date": "2019-01-29 20:00:00",
      "player_assisted": "Ashley Barnes",
      "lastAction": "BallTouch"
    },
    {
      "id": "274981",
      "minute": "17",
      "result": "BlockedShot",
      "X": "0.965999984741211",
      "Y": "0.6",
      "xG": "0.02770249918103218",
      "player": "Chris Wood",
      "h_a": "a",
      "player_id": "4456",
      "situation": "FromCorner",
      "season": "2018",
      "shotType": "Head",
      "match_id": "9432",
      "h_team": "Manchester United",
      "a_team": "Burnley",
      "h_goals": "2",
      "a_goals": "2",
      "date": "2019-01-29 20:00:00",
      "player_assisted": "Dwight McNeil",
      "lastAction": "CornerAwarded"
    },
    {
      "id": "274990",
      "minute": "50",
      "result": "Goal",
      "X": "0.8780000305175781",
      "Y": "0.580999984741211",
      "xG": "0.34278300404548645",
      "player": "Ashley Barnes",
      "h_a": "a",
      "player_id": "4422",
      "situation": "OpenPlay",
      "season": "2018",
      "shotType": "LeftFoot",
      "match_id": "9432",
      "h_team": "Manchester United",
      "a_team": "Burnley",
      "h_goals": "2",
      "a_goals": "2",
      "date": "2019-01-29 20:00:00",
      "player_assisted": "Jack Cork",
      "lastAction": "Pass"
    },
    {
      "id": "274995",
      "minute": "56",
      "result": "SavedShot",
      "X": "0.8009999847412109",
      "Y": "0.2520000076293945",
      "xG": "0.02182989940047264",
      "player": "Dwight McNeil",
      "h_a": "a",
      "player_id": "6756",
      "situation": "OpenPlay",
      "season": "2018",
      "shotType": "LeftFoot",
      "match_id": "9432",
      "h_team": "Manchester United",
      "a_team": "Burnley",
      "h_goals": "2",
      "a_goals": "2",
      "date": "2019-01-29 20:00:00",
      "player_assisted": "Jeff Hendrick",
      "lastAction": "Pass"
    },
    {
      "id": "275003",
      "minute": "80",
      "result": "Goal",
      "X": "0.9330000305175781",
      "Y": "0.54",
      "xG": "0.48670199513435364",
      "player": "Chris Wood",
      "h_a": "a",
      "player_id": "4456",
      "situation": "OpenPlay",
      "season": "2018",
      "shotType": "Head",
      "match_id": "9432",
      "h_team": "Manchester United",
      "a_team": "Burnley",
      "h_goals": "2",
      "a_goals": "2",
      "date": "2019-01-29 20:00:00",
      "player_assisted": "Ashley Westwood",
      "lastAction": "Aerial"
    }
  ]
}